README
setup.py
multimethods/__init__.py
multimethods.egg-info/PKG-INFO
multimethods.egg-info/SOURCES.txt
multimethods.egg-info/dependency_links.txt
multimethods.egg-info/top_level.txt
tests/__init__.py
tests/test_multimethod.py