Metadata-Version: 1.0
Name: multimethods
Version: 1.0.0
Summary: A simple python multidispatch.
Home-page: http://packages.python.org/multimethods
Author: Robert Kende
Author-email: robert.kende@gmail.com
License: MIT
Keywords: multimethods,multidispatch,dispatch,decorator
Platform: UNKNOWN
Classifier: Development Status :: 5 - Production/Stable
Classifier: Programming Language :: Python
Classifier: Intended Audience :: Developers
Classifier: Topic :: Software Development
Classifier: License :: OSI Approved :: MIT License
